owlplanner/__init__.py
owlplanner/abcapi.py
owlplanner/config.py
owlplanner/debts.py
owlplanner/fixedassets.py
owlplanner/mylogging.py
owlplanner/plan.py
owlplanner/progress.py
owlplanner/rates.py
owlplanner/socialsecurity.py
owlplanner/tax2025.py
owlplanner/tax2026.py
owlplanner/timelists.py
owlplanner/utils.py
owlplanner/version.py
owlplanner/data/__init__.py
owlplanner/data/awi.csv
owlplanner/data/bendpoints.csv
owlplanner/data/newawi.csv
owlplanner/data/rates.csv
owlplanner/plotting/__init__.py
owlplanner/plotting/base.py
owlplanner/plotting/factory.py
owlplanner/plotting/matplotlib_backend.py
owlplanner/plotting/plotly_backend.py
owlplanner-2025.12.20.dist-info/METADATA
owlplanner-2025.12.20.dist-info/WHEEL
owlplanner-2025.12.20.dist-info/licenses/LICENSE
owlplanner-2025.12.20.dist-info/RECORD
