Metadata-Version: 2.4
Name: owlplanner
Version: 2025.12.20
Summary: Owl - Optimal Wealth Lab: Retirement planner with great wisdom
Project-URL: HomePage, https://github.com/mdlacasse/owl
Project-URL: Repository, https://github.com/mdlacasse/owl
Project-URL: Issues, https://github.com/mdlacasse/owl/issues
Project-URL: Documentation, https://github.com/mdlacasse/Owl/blob/main/docs/owl.pdf
Project-URL: DOWNLOAD, https://github.com/mdlacasse/Owl/archive/refs/heads/main.zip
Author-email: "Martin-D. Lacasse" <martin.d.lacasse@gmail.com>
Maintainer-email: "Martin-D. Lacasse" <martin.d.lacasse@gmail.com>
License:                     GNU GENERAL PUBLIC LICENSE
License-File: LICENSE
Classifier: Development Status :: 5 - Production/Stable
Classifier: Intended Audience :: End Users/Desktop
Classifier: License :: OSI Approved :: GNU General Public License v3 (GPLv3)
Classifier: Operating System :: OS Independent
Classifier: Programming Language :: Python :: 3
Classifier: Topic :: Office/Business :: Financial :: Investment
Requires-Python: >=3.10
Requires-Dist: highspy
Requires-Dist: jupyter>=1.1.1
Requires-Dist: matplotlib
Requires-Dist: numpy
Requires-Dist: odfpy
Requires-Dist: openpyxl
Requires-Dist: pandas
Requires-Dist: plotly>=6.3
Requires-Dist: pulp
Requires-Dist: pyyaml>=6.0.3
Requires-Dist: scipy
Requires-Dist: seaborn
Requires-Dist: streamlit
Requires-Dist: toml
